pd_httprequest_util/__init__.py
pd_httprequest_util/connection/__init__.py
pd_httprequest_util/connection/async_.py
pd_httprequest_util/connection/main.py
pd_httprequest_util/connection/sync_.py
pd_httprequest_util/request.py
pd_httprequest_util/request_manager.py
pd_httprequest_util/utils/__init__.py
pd_httprequest_util/utils/group_util.py
pd_httprequest_util/utils/log_util.py
pd_httprequest_util-0.1.0.dist-info/WHEEL
pd_httprequest_util-0.1.0.dist-info/METADATA
pd_httprequest_util-0.1.0.dist-info/RECORD
