Metadata-Version: 2.1
Name: pd-httprequest-util
Version: 0.1.0
Summary: http request util with both sync/async method.provide with concurrency control；iter retrn；log
Home-page: https://github.com/pillipanda/pd_httprequest_util
License: MIT
Author: 彭泗雄
Author-email: pillipanda@126.com
Requires-Python: >=3.7,<4.0
Classifier: License :: OSI Approved :: MIT License
Classifier: Programming Language :: Python :: 3
Classifier: Programming Language :: Python :: 3.7
Classifier: Programming Language :: Python :: 3.8
Requires-Dist: aiodns (>=2.0.0,<3.0.0)
Requires-Dist: aiohttp (>=3.6.2,<4.0.0)
Requires-Dist: loguru (>=0.5.1,<0.6.0)
Requires-Dist: requests (>=2.24.0,<3.0.0)
Requires-Dist: ujson (>=3.1.0,<4.0.0)
Project-URL: Repository, https://github.com/pillipanda/pd_httprequest_util
